unified_plotting/__init__.py
unified_plotting/_logging.py
unified_plotting/_config/__init__.py
unified_plotting/_config/config.py
unified_plotting/_config/settings.json
unified_plotting/_unified_arguments/__init__.py
unified_plotting/_unified_arguments/arguments.py
unified_plotting/_unified_arguments/injection.py
unified_plotting/_unified_arguments/shared_preprocessing.py
unified_plotting/_unified_arguments/shared_processing.py
unified_plotting/_unified_arguments/colormaps/__init__.py
unified_plotting/_unified_arguments/colormaps/colormaps.py
unified_plotting/_unified_arguments/colors/__init__.py
unified_plotting/_unified_arguments/colors/conversion.py
unified_plotting/_unified_arguments/colors/named_colors.py
unified_plotting/javascript/__init__.py
unified_plotting/javascript/_data_structures.py
unified_plotting/javascript/_plots_external.py
unified_plotting/javascript/_plots_nd.py
unified_plotting/javascript/_plots_network.py
unified_plotting/javascript/_template_system.py
unified_plotting/javascript/templates/image_viewer.html
unified_plotting/javascript/templates/network_d3.html
unified_plotting/javascript/templates/network_vis.html
unified_plotting/javascript/templates/network_webgl.html
unified_plotting/javascript/templates/pc_table_parcoords_slickgrid.html
unified_plotting/javascript/templates/table_slickgrid.html
unified_plotting/javascript/third_party/3d-force-graph/3d-force-graph.min.def.js
unified_plotting/javascript/third_party/3d-force-graph/ORIGINAL_LICENSE
unified_plotting/javascript/third_party/d3/ORIGINAL_LICENSE
unified_plotting/javascript/third_party/d3/d3.v5.min.def.js
unified_plotting/javascript/third_party/d3-color/ORIGINAL_LICENSE
unified_plotting/javascript/third_party/d3-color/d3-color.v1.min.def.js
unified_plotting/javascript/third_party/d3-interpolate/ORIGINAL_LICENSE
unified_plotting/javascript/third_party/d3-interpolate/d3-interpolate.v1.min.def.js
unified_plotting/javascript/third_party/d3-scale-chromatic/ORIGINAL_LICENSE
unified_plotting-0.5.0rc1.dist-info/LICENSE
unified_plotting-0.5.0rc1.dist-info/METADATA
unified_plotting-0.5.0rc1.dist-info/WHEEL
unified_plotting-0.5.0rc1.dist-info/entry_points.txt
unified_plotting-0.5.0rc1.dist-info/top_level.txt
unified_plotting-0.5.0rc1.dist-info/RECORD
