Metadata-Version: 2.1
Name: unified-plotting
Version: 0.5.0rc1
Summary: Quick and easy plotting of tabular and network data.
Home-page: https://robert-haas.github.io/unified-plotting-docs/
Author: Robert Haas
Author-email: robert.haas@protonmail.com
License: Apache License, Version 2.0
Platform: UNKNOWN
Classifier: Development Status :: 4 - Beta
Classifier: Intended Audience :: Developers
Classifier: Intended Audience :: Education
Classifier: Intended Audience :: Science/Research
Classifier: License :: OSI Approved :: Apache Software License
Classifier: Natural Language :: English
Classifier: Operating System :: OS Independent
Classifier: Programming Language :: Python :: 3
Classifier: Programming Language :: Python :: 3.6
Classifier: Programming Language :: Python :: 3.7
Classifier: Programming Language :: Python :: 3.8
Classifier: Topic :: Multimedia :: Graphics
Classifier: Topic :: Multimedia :: Graphics :: Presentation
Classifier: Topic :: Multimedia :: Graphics :: 3D Rendering
Classifier: Topic :: Scientific/Engineering
Classifier: Topic :: Scientific/Engineering :: Visualization
Requires-Python: >=3.6
Requires-Dist: matplotlib (<4,>=3.1)
Requires-Dist: plotly (!=4.7.0,<5,>=4.5)
Requires-Dist: setuptools (>=40.0)
Requires-Dist: numpy (<2,>=1.17.4)
Requires-Dist: scipy (<2,>=1.4)
Requires-Dist: psutil (<6,>=5.4.5)
Requires-Dist: requests (<3,>=2)
Requires-Dist: flask (<2,>=1.1)
Requires-Dist: waitress (<2,>=1.4)
